levelorm/__init__.py
levelorm/exceptions.py
levelorm/fields.py
levelorm/orm.py
levelorm-0.2.dist-info/DESCRIPTION.rst
levelorm-0.2.dist-info/METADATA
levelorm-0.2.dist-info/RECORD
levelorm-0.2.dist-info/WHEEL
levelorm-0.2.dist-info/metadata.json
levelorm-0.2.dist-info/top_level.txt
levelorm-0.2.dist-info/zip-safe
