Metadata-Version: 2.0
Name: levelorm
Version: 0.2
Summary: python3.6+ ORM for leveldb using plyvel
Home-page: http://github.com/raylu/levelorm
Author: raylu
Author-email: raylu@users.noreply.github.com
License: UNKNOWN
Platform: UNKNOWN
Requires-Python: >=3.6
Requires-Dist: plyvel
